nlopt/__init__.py
nlopt/_nlopt.pyd
nlopt/nlopt.py
nlopt-2.9.1.dist-info/LICENSE
nlopt-2.9.1.dist-info/METADATA
nlopt-2.9.1.dist-info/WHEEL
nlopt-2.9.1.dist-info/top_level.txt
nlopt-2.9.1.dist-info/RECORD
