Metadata-Version: 2.2
Name: nlopt
Version: 2.9.1
Summary: Library for nonlinear optimization, wrapping many algorithms for global and local, constrained or unconstrained, optimization
Author: Daniel Bok
Author-email: daniel.bok@outlook.com
Maintainer: Daniel Bok
Maintainer-email: daniel.bok@outlook.com
License: MIT
Project-URL: Documentation, https://nlopt.readthedocs.io/en/latest/
Project-URL: Code, https://github.com/DanielBok/nlopt-python
Project-URL: Issue tracker, https://github.com/DanielBok/nlopt-python/issues
Keywords: algorithms,global local constrained unconstrained optimization,optimization,non-linear optimization
Classifier: Development Status :: 5 - Production/Stable
Classifier: Intended Audience :: End Users/Desktop
Classifier: Intended Audience :: Education
Classifier: License :: OSI Approved :: MIT License
Classifier: Operating System :: MacOS
Classifier: Operating System :: Microsoft :: Windows
Classifier: Operating System :: Unix
Classifier: Programming Language :: C++
Classifier: Programming Language :: Python :: 3.9
Classifier: Programming Language :: Python :: 3.10
Classifier: Programming Language :: Python :: 3.11
Classifier: Programming Language :: Python :: 3.12
Classifier: Programming Language :: Python :: 3.13
Classifier: Topic :: Scientific/Engineering
Requires-Python: >=3.9
License-File: LICENSE
Requires-Dist: numpy<3,>=2
Dynamic: requires-dist
Dynamic: requires-python
